{"cameraMode":{"drawMode":0,"name":"Shaded","section":"Shading Mode"},"sceneLighting":false,"audioPlay":false,"sceneViewState":{"showFog":true,"showMaterialUpdate":false,"showSkybox":false,"showFlares":true,"showImageEffects":true,"showParticleSystems":true},"in2DMode":false,"pivot":{"x":-909.246826171875,"y":-806.5604858398438,"z":1880.312255859375},"rotation":{"x":0.1745973527431488,"y":-0.26656967401504519,"z":0.04916784167289734,"w":0.9465941190719605},"size":4965.3681640625,"orthographic":false}