{"cameraMode":{"drawMode":0,"name":"Shaded","section":"Shading Mode"},"sceneLighting":false,"audioPlay":false,"sceneViewState":{"showFog":true,"showMaterialUpdate":false,"showSkybox":false,"showFlares":true,"showImageEffects":true,"showParticleSystems":true},"in2DMode":false,"pivot":{"x":-121.4024658203125,"y":96.7145767211914,"z":-139.78697204589845},"rotation":{"x":-0.09499568492174149,"y":-0.7231633067131043,"z":0.10153968632221222,"w":-0.6765388250350952},"size":198.51231384277345,"orthographic":false}